  [{"id":"1258","categoryID":"0","getFromList":"PLX2E6b7TzXuRRlNmx9sxLE4StSviNDLo3","videoDuration":"00:10:16","videoID":"E7ChWrUuh4M","videosName":"DldH #166: DSH-MODELLPR\u00dcFUNG: H\u00d6RVERSTEHEN | Der Phono sapiens"},{"id":"1264","categoryID":"0","getFromList":"PLX2E6b7TzXuRRlNmx9sxLE4StSviNDLo3","videoDuration":"00:02:31","videoID":"z8YInXZz3T0","videosName":"Deutsch lernen durch H\u00f6ren #116: Wer war das? Wer hat alle meine Sachen versteckt?"},{"id":"1265","categoryID":"0","getFromList":"PLX2E6b7TzXuRRlNmx9sxLE4StSviNDLo3","videoDuration":"00:01:11","videoID":"14Z2V67m75Y","videosName":"DldH #185: Bei der Verbraucherzentrale arbeiten [verbessert]"},{"id":"1266","categoryID":"0","getFromList":"PLX2E6b7TzXuRRlNmx9sxLE4StSviNDLo3","videoDuration":"00:10:23","videoID":"TFs311NvKtA","videosName":"Deutsch lernen durch H\u00f6ren #187: 5 Dialoge zum Deutsch lernen"},{"id":"1267","categoryID":"0","getFromList":"PLX2E6b7TzXuRRlNmx9sxLE4StSviNDLo3","videoDuration":"00:10:06","videoID":"PlR9L5AHGDY","videosName":"Deutsch lernen durch H\u00f6ren #188: 4 Dialoge zum Deutsch lernen"},{"id":"1268","categoryID":"0","getFromList":"PLX2E6b7TzXuRRlNmx9sxLE4StSviNDLo3","videoDuration":"00:04:42","videoID":"bo8daQ4z8l0","videosName":"Deutsch lernen durch H\u00f6ren #110: Das deutsche Slow-Lied | Ist es wahr?"},{"id":"1269","categoryID":"0","getFromList":"PLX2E6b7TzXuRRlNmx9sxLE4StSviNDLo3","videoDuration":"00:02:20","videoID":"fwABFCRgp-I","videosName":"Deutsch lernen durch H\u00f6ren #100: Lustiger Song auf Deutsch"},{"id":"1270","categoryID":"0","getFromList":"PLX2E6b7TzXuRRlNmx9sxLE4StSviNDLo3","videoDuration":"00:04:15","videoID":"pDL2nb9eT_s","videosName":"DldH #91: Das lustige Lied auf Deutsch(mit Untertitel) | Ihr schmeckt Kaffee, mir schmeckt Tee"},{"id":"1271","categoryID":"0","getFromList":"PLX2E6b7TzXuRRlNmx9sxLE4StSviNDLo3","videoDuration":"00:02:17","videoID":"vLTPO0Cc8pE","videosName":"Deutsch lernen durch H\u00f6ren #175: Klaus hat einige M\u00e4dchen zum Weinen gebracht!"},{"id":"1272","categoryID":"0","getFromList":"PLX2E6b7TzXuRRlNmx9sxLE4StSviNDLo3","videoDuration":"00:01:19","videoID":"EzYBUIRFHAY","videosName":"Deutsch lernen durch H\u00f6ren #174: Ist der Computer Zeitfresser?"},{"id":"1273","categoryID":"0","getFromList":"PLX2E6b7TzXuRRlNmx9sxLE4StSviNDLo3","videoDuration":"00:01:24","videoID":"YHYgn02TcL4","videosName":"DldH #173: Gespr\u00e4ch am Telefon | Ich f\u00fchle mich schon  fast wie Deutscher!"},{"id":"1274","categoryID":"0","getFromList":"PLX2E6b7TzXuRRlNmx9sxLE4StSviNDLo3","videoDuration":"00:17:29","videoID":"g2xLpc6IlCs","videosName":"Deutsch lernen durch H\u00f6ren #194: H\u00e4nsel und Gretel - M\u00e4rchen der Br\u00fcder Grimm(mit Untertiteln)"}]