  [{"id":"143","categoryID":"0","getFromList":"PLneqwMJNfnlCpRPMfPeFzV_97zUkuKFXl","videoDuration":"00:08:25","videoID":"hRJdE5pc84Y","videosName":"Deutsch lernen: E-Mails schreiben - Teil 1"},{"id":"144","categoryID":"0","getFromList":"PLneqwMJNfnlCpRPMfPeFzV_97zUkuKFXl","videoDuration":"00:07:04","videoID":"on2eo4k_UZw","videosName":"Deutsch lernen: E-Mails schreiben - Teil 2"},{"id":"145","categoryID":"0","getFromList":"PLneqwMJNfnlCpRPMfPeFzV_97zUkuKFXl","videoDuration":"00:04:37","videoID":"4BRanL-nREE","videosName":"Deutsch lernen: E-Mails schreiben - Teil 3"},{"id":"146","categoryID":"0","getFromList":"PLneqwMJNfnlCpRPMfPeFzV_97zUkuKFXl","videoDuration":"00:27:36","videoID":"Ix5FTQZ2mt4","videosName":"celeco - Richtig Schreiben Lernen"},{"id":"147","categoryID":"0","getFromList":"PLneqwMJNfnlCpRPMfPeFzV_97zUkuKFXl","videoDuration":"00:02:52","videoID":"1Jy3uqFYntw","videosName":"Soft Skills Email richtig schreiben"},{"id":"148","categoryID":"0","getFromList":"PLneqwMJNfnlCpRPMfPeFzV_97zUkuKFXl","videoDuration":"00:04:15","videoID":"LKBfGmeeGqc","videosName":"German Lesson: How to write a letter - Niveau A1"}]