  [{"id":"229","categoryID":"0","getFromList":"PLTvFTxkaQpg40iLdjkK53KTVjJmoxMx5R","videoDuration":"3:54","videoID":"X-h4tC7-mPc","videosName":"Der deutsche Umlaut \u00dc - The German umlaut \u00dc (Tutorial)"},{"id":"230","categoryID":"0","getFromList":"PLTvFTxkaQpg40iLdjkK53KTVjJmoxMx5R","videoDuration":"2:44","videoID":"mKbcDYszrmM","videosName":"Deutsch: Aussprache von \u00d6, \u00dc (deutsche Untertitel)\/Pronunciation of \u00d6, \u00dc (German subtitles)"},{"id":"231","categoryID":"0","getFromList":"PLTvFTxkaQpg40iLdjkK53KTVjJmoxMx5R","videoDuration":"5:30","videoID":"gfieYag3NOU","videosName":"Deutsch lernen A1: ein, eine, kein, keine im Nominativ - Schritte plus 1 Lektion 3 (B3)"},{"id":"232","categoryID":"0","getFromList":"PLTvFTxkaQpg40iLdjkK53KTVjJmoxMx5R","videoDuration":"4:36","videoID":"l5GG1Me6qWE","videosName":"Deutsch: Aussprache von \u00c4, E, I (deutsche Untertitel)\/Pronunciation of \u00c4, E, I (German subtitles)"},{"id":"233","categoryID":"0","getFromList":"PLTvFTxkaQpg40iLdjkK53KTVjJmoxMx5R","videoDuration":"5:58","videoID":"VhUQvrnNtWo","videosName":"Der deutsche Umlaut \u00d6 - The German umlaut \u00d6 (Tutorial)"},{"id":"234","categoryID":"0","getFromList":"PLTvFTxkaQpg40iLdjkK53KTVjJmoxMx5R","videoDuration":"3:35","videoID":"OGwmiY4wcrs","videosName":"How to pronounce the german Umlaut \"\u00fc\""},{"id":"235","categoryID":"0","getFromList":"PLTvFTxkaQpg40iLdjkK53KTVjJmoxMx5R","videoDuration":"3:4","videoID":"Q_hWn9uWTTw","videosName":"Deutsch lernen: Aussprache von -e und -er \/ German: pronunciation of e and er"},{"id":"236","categoryID":"0","getFromList":"PLTvFTxkaQpg40iLdjkK53KTVjJmoxMx5R","videoDuration":"10:3","videoID":"Lx1UtcjxwQ4","videosName":"Deutsch Extra: Aussprache von R"},{"id":"237","categoryID":"0","getFromList":"PLTvFTxkaQpg40iLdjkK53KTVjJmoxMx5R","videoDuration":"2:27","videoID":"g8Rfl4ef038","videosName":"Deutsch lernen: Aussprache von gehen, sehen, stehen\/German: pronunciation of gehen, sehen, stehen"},{"id":"238","categoryID":"0","getFromList":"PLTvFTxkaQpg40iLdjkK53KTVjJmoxMx5R","videoDuration":"0:3","videoID":"7EgrFYlQ0a4","videosName":"Deutsch lernen! Aussprache von Konsonanten am Wortende: typische Fehler"},{"id":"239","categoryID":"0","getFromList":"PLTvFTxkaQpg40iLdjkK53KTVjJmoxMx5R","videoDuration":"2:52","videoID":"EHlGR6CAr-8","videosName":"Aussprache der Laute: ei, ie, \u00f6 und \u00fc"}]