  [{"id":"573","categoryID":"0","getFromList":"PLX2E6b7TzXuSAy7I8uqqW-UtsvCYAfEBd","videoDuration":"00:01:25","videoID":"iZeTSIHah5c","videosName":"Deutsch lernen durch H\u00f6ren #60: schnell schnell, du hast doch eine Porsche!"},{"id":"574","categoryID":"0","getFromList":"PLX2E6b7TzXuSAy7I8uqqW-UtsvCYAfEBd","videoDuration":"00:00:01","videoID":"S-bykF8uMfg","videosName":"Deutsch lernen durch H\u00f6ren - H\u00f6r mal! | #44: Erstmal Bier und dann Zeitung"},{"id":"581","categoryID":"0","getFromList":"PLX2E6b7TzXuSAy7I8uqqW-UtsvCYAfEBd","videoDuration":"00:01:48","videoID":"-AFEyiAe5D4","videosName":"Deutsch lernen durch H\u00f6ren - H\u00f6r mal!#35 :Tapete mit Blumen-3"},{"id":"582","categoryID":"0","getFromList":"PLX2E6b7TzXuSAy7I8uqqW-UtsvCYAfEBd","videoDuration":"00:01:59","videoID":"3Et2_Q0tooY","videosName":"Deutsch lernen durch H\u00f6ren | #25: Ich habe mich mit dem Chef nicht verstanden"}]