  [{"id":"110","categoryID":"0","getFromList":"PLID3ddg2-Aj7_mVRGkcMmKnQP-L99Womz","videoDuration":"2:56","videoID":"E4Ce4XyBV6A","videosName":"German Vocabulary Course [01] Tiere | Deutsch Vokabeln"},{"id":"111","categoryID":"0","getFromList":"PLID3ddg2-Aj7_mVRGkcMmKnQP-L99Womz","videoDuration":"2:18","videoID":"Zhz2S8GXAyA","videosName":"German Vocabulary Course [02] Haus | Deutsch Vokabeln"},{"id":"112","categoryID":"0","getFromList":"PLID3ddg2-Aj7_mVRGkcMmKnQP-L99Womz","videoDuration":"2:12","videoID":"GbbHatBwkKM","videosName":"German Vocabulary Course [03] Wohnzimmer | Deutsch Vokabeln"},{"id":"113","categoryID":"0","getFromList":"PLID3ddg2-Aj7_mVRGkcMmKnQP-L99Womz","videoDuration":"2:5","videoID":"Zs1YtgjqRlU","videosName":"German Vocabulary Course [04] K\u00f6rper | Deutsch Vokabeln"},{"id":"114","categoryID":"0","getFromList":"PLID3ddg2-Aj7_mVRGkcMmKnQP-L99Womz","videoDuration":"2:5","videoID":"S4eUY2VUemY","videosName":"German Vocabulary Course [05] Gesicht | Deutsch Vokabeln"},{"id":"115","categoryID":"0","getFromList":"PLID3ddg2-Aj7_mVRGkcMmKnQP-L99Womz","videoDuration":"2:5","videoID":"UxBj-NxiPs8","videosName":"German Vocabulary Course [06] Farben | Deutsch Vokabeln"},{"id":"116","categoryID":"0","getFromList":"PLID3ddg2-Aj7_mVRGkcMmKnQP-L99Womz","videoDuration":"2:22","videoID":"fB2GpUzN7sk","videosName":"German Vocabulary Course [07] Fahrzeuge | Deutsch Vokabeln"},{"id":"117","categoryID":"0","getFromList":"PLID3ddg2-Aj7_mVRGkcMmKnQP-L99Womz","videoDuration":"2:11","videoID":"hDEnwmTMTkE","videosName":"German Vocabulary Course [08] Badezimmer | Deutsch Vokabeln"},{"id":"118","categoryID":"0","getFromList":"PLID3ddg2-Aj7_mVRGkcMmKnQP-L99Womz","videoDuration":"2:10","videoID":"zf8mZijDSbM","videosName":"German Vocabulary Course [09] Kleidung | Deutsch Vokabeln"},{"id":"119","categoryID":"0","getFromList":"PLID3ddg2-Aj7_mVRGkcMmKnQP-L99Womz","videoDuration":"2:10","videoID":"6yqIaumqF3E","videosName":"German Vocabulary Course [10] Geschirr | Deutsch Vokabeln"},{"id":"120","categoryID":"0","getFromList":"PLID3ddg2-Aj7_mVRGkcMmKnQP-L99Womz","videoDuration":"2:16","videoID":"3z8m1Xc-9e8","videosName":"German Vocabulary Course [11] Werkzeug | Deutsch Vokabeln"},{"id":"121","categoryID":"0","getFromList":"PLID3ddg2-Aj7_mVRGkcMmKnQP-L99Womz","videoDuration":"2:12","videoID":"ZVNHe2LJxH0","videosName":"German Vocabulary Course [12] Obst | Deutsch Vokabeln"},{"id":"122","categoryID":"0","getFromList":"PLID3ddg2-Aj7_mVRGkcMmKnQP-L99Womz","videoDuration":"2:16","videoID":"dIMv01X2OhY","videosName":"German Vocabulary Course [13] Gem\u00fcse | Deutsch Vokabeln"},{"id":"123","categoryID":"0","getFromList":"PLID3ddg2-Aj7_mVRGkcMmKnQP-L99Womz","videoDuration":"2:16","videoID":"fUwRtkdek8I","videosName":"German Vocabulary Course [14] Musikinstrumente | Deutsch Vokabeln"},{"id":"124","categoryID":"0","getFromList":"PLID3ddg2-Aj7_mVRGkcMmKnQP-L99Womz","videoDuration":"2:15","videoID":"De8CCulb9J4","videosName":"German Vocabulary Course [15] Familie | Deutsch Vokabeln"},{"id":"125","categoryID":"0","getFromList":"PLID3ddg2-Aj7_mVRGkcMmKnQP-L99Womz","videoDuration":"2:12","videoID":"s7hj9aHyEqs","videosName":"German Vocabulary Course [16] Gef\u00fchle | Deutsch Vokabeln"},{"id":"126","categoryID":"0","getFromList":"PLID3ddg2-Aj7_mVRGkcMmKnQP-L99Womz","videoDuration":"3:1","videoID":"3FUQqhK2Ewk","videosName":"German Vocabulary Course [17] Haare | Deutsch Vokabeln"},{"id":"127","categoryID":"0","getFromList":"PLID3ddg2-Aj7_mVRGkcMmKnQP-L99Womz","videoDuration":"2:35","videoID":"SdFczLahc5Y","videosName":"German Vocabulary Course [18] Krankheit | Deutsch Vokabeln"},{"id":"128","categoryID":"0","getFromList":"PLID3ddg2-Aj7_mVRGkcMmKnQP-L99Womz","videoDuration":"3:11","videoID":"znYJIRizd7M","videosName":"German Vocabulary Course [19] Tasche | Deutsch Vokabeln"},{"id":"129","categoryID":"0","getFromList":"PLID3ddg2-Aj7_mVRGkcMmKnQP-L99Womz","videoDuration":"3:30","videoID":"J1jQP8-2dY8","videosName":"German Vocabulary Course [20] Verletzungen (injuries) | Deutsch Vokabeln"},{"id":"130","categoryID":"0","getFromList":"PLID3ddg2-Aj7_mVRGkcMmKnQP-L99Womz","videoDuration":"8:9","videoID":"dz0me293MZA","videosName":"German Vocabulary Trainer \u2606 basic words"},{"id":"131","categoryID":"0","getFromList":"PLID3ddg2-Aj7_mVRGkcMmKnQP-L99Womz","videoDuration":"6:27","videoID":"AkU_9DKjwko","videosName":"German Vocabulary Trainer \u2606 countries (L\u00e4nder)"},{"id":"132","categoryID":"0","getFromList":"PLID3ddg2-Aj7_mVRGkcMmKnQP-L99Womz","videoDuration":"9:2","videoID":"Jpk9Ja154Z4","videosName":"German Vocabulary Course [21] Kitchen Electricals"},{"id":"133","categoryID":"0","getFromList":"PLID3ddg2-Aj7_mVRGkcMmKnQP-L99Womz","videoDuration":"9:45","videoID":"ZcJbGr4e9rc","videosName":"German Vocabulary Course [22] Office Supplies"},{"id":"134","categoryID":"0","getFromList":"PLID3ddg2-Aj7_mVRGkcMmKnQP-L99Womz","videoDuration":"8:20","videoID":"U40cs49nIdU","videosName":"German Vocabulary Course [23] Winter Clothes"}]