  [{"id":"3284","categoryID":"5","getFromList":"PL8PwfU8m5_hrtL2-b-fqtv4l2-HnAG1fM","videoDuration":"15:6","videoID":"ON0QUKZdpcM","videosName":"Lektion 11 - Nominativ & Gi\u1ed1ng c\u1ee7a danh t\u1eeb (Genus)"},{"id":"3285","categoryID":"5","getFromList":"PL8PwfU8m5_hrtL2-b-fqtv4l2-HnAG1fM","videoDuration":"10:42","videoID":"DHaoGsrvkvM","videosName":"Lektion 12 - Gi\u1edbi t\u1eeb ch\u1ec9 v\u1ecb tr\u00ed (Wechselpr\u00e4positionen)"},{"id":"3286","categoryID":"5","getFromList":"PL8PwfU8m5_hrtL2-b-fqtv4l2-HnAG1fM","videoDuration":"12:41","videoID":"T0b7HC0EbEQ","videosName":"Lektion 16 - Pluralbildung (Th\u00e0nh l\u1eadp d\u1ea1ng s\u1ed1 nhi\u1ec1u cho danh t\u1eeb)"},{"id":"3287","categoryID":"5","getFromList":"PL8PwfU8m5_hrtL2-b-fqtv4l2-HnAG1fM","videoDuration":"10:55","videoID":"KOaUEIBw_J4","videosName":"Lektion 17 - Possessivpronomen (\u0110\u1ea1i t\u1eeb s\u1edf h\u1eefu)"},{"id":"3290","categoryID":"5","getFromList":"PL8PwfU8m5_hrtL2-b-fqtv4l2-HnAG1fM","videoDuration":"7:49","videoID":"CuYJgCOCAoY","videosName":"Lektion 23 - Reflexivpronomen - \u0110\u1ea1i t\u1eeb ph\u1ea3n th\u00e2n"},{"id":"3291","categoryID":"5","getFromList":"PL8PwfU8m5_hrtL2-b-fqtv4l2-HnAG1fM","videoDuration":"7:51","videoID":"gydIneR-4os","videosName":"Lektion 24 - Reflexivverben - \u0110\u1ed9ng t\u1eeb ph\u1ea3n th\u00e2n"},{"id":"3292","categoryID":"5","getFromList":"PL8PwfU8m5_hrtL2-b-fqtv4l2-HnAG1fM","videoDuration":"8:32","videoID":"CMBU717KKFI","videosName":"Lektion 26  ? Satzbau ? Th\u00e0nh l\u1eadp c\u00e2u"},{"id":"3293","categoryID":"5","getFromList":"PL8PwfU8m5_hrtL2-b-fqtv4l2-HnAG1fM","videoDuration":"9:14","videoID":"3FPyDDq0WGc","videosName":"Lektion 27 ? Verneinung - \"kein\" oder \"nicht\"? (C\u00e2u ph\u1ee7 \u0111\u1ecbnh)"},{"id":"3294","categoryID":"5","getFromList":"PL8PwfU8m5_hrtL2-b-fqtv4l2-HnAG1fM","videoDuration":"8:34","videoID":"hVTtC5w_4b0","videosName":"Lektion 28 ? Perfekt - haben\/sein? (Th\u1ec3 qu\u00e1 kh\u1ee9)"},{"id":"3295","categoryID":"5","getFromList":"PL8PwfU8m5_hrtL2-b-fqtv4l2-HnAG1fM","videoDuration":"20:4","videoID":"kxACh14o0lU","videosName":"Lektion 29 ? Kasus - Ph\u00e2n bi\u1ec7t c\u00e1c c\u00e1ch trong ti\u1ebfng \u0110\u1ee9c"},{"id":"3296","categoryID":"5","getFromList":"PL8PwfU8m5_hrtL2-b-fqtv4l2-HnAG1fM","videoDuration":"13:16","videoID":"lm7U5y38d38","videosName":"Lektion 30 ? Artikeldeklination - Chia m\u1ea1o t\u1eeb theo c\u00e1c c\u00e1ch (Kasus)"},{"id":"3298","categoryID":"5","getFromList":"PL8PwfU8m5_hrtL2-b-fqtv4l2-HnAG1fM","videoDuration":"19:51","videoID":"Pn9fY4DfV3M","videosName":"Lektion 32 ? Adjektivdeklination - Chia \u0111u\u00f4i t\u00ednh t\u1eeb"}]